bqtmizer/__init__.py
bqtmizer/bootqa.py
bqtmizer/core.py
demo/__init__.py
demo/bqtmizer_test.py
bqtmizer-1.0.2.dist-info/LICENSE
bqtmizer-1.0.2.dist-info/METADATA
bqtmizer-1.0.2.dist-info/WHEEL
bqtmizer-1.0.2.dist-info/top_level.txt
bqtmizer-1.0.2.dist-info/RECORD
