Metadata-Version: 2.1
Name: bqtmizer
Version: 1.0.2
Summary: BQTmizer: A Tool for Test Case Minimization with Quantum Annealing
Home-page: https://github.com/qiqihannah/BQTmizer
Author: Xinyi Wang
Author-email: xinyi@simula.no
Classifier: Programming Language :: Python :: 3
Classifier: License :: OSI Approved :: MIT License
Classifier: Operating System :: OS Independent
Requires-Python: >=3.8
License-File: LICENSE
Requires-Dist: dimod ==0.12.17
Requires-Dist: dwave-system ==1.26.0
Requires-Dist: dwave-inspector ==0.5.1
Requires-Dist: pandas
